uGMRT_beamtool/__init__.py
uGMRT_beamtool/make_ds.py
uGMRT_beamtool/plot_uGMRT_ds.py
uGMRT_beamutils/__init__.py
uGMRT_beamutils/gptool.in
uGMRT_beamutils/template.gmrt.hdr
uGMRT_beamutils/gptool_ver4.2.1/acqpsr.h
uGMRT_beamutils/gptool_ver4.2.1/corr1.h
uGMRT_beamutils/gptool_ver4.2.1/cpgplot.h
uGMRT_beamutils/gptool_ver4.2.1/gmrt_newcorr.h
uGMRT_beamutils/gptool_ver4.2.1/gptool
uGMRT_beamutils/gptool_ver4.2.1/gptool.cpp
uGMRT_beamutils/gptool_ver4.2.1/libcpgplot.a
uGMRT_beamutils/gptool_ver4.2.1/libpgplot.a
uGMRT_beamutils/gptool_ver4.2.1/libshm.a
uGMRT_beamutils/gptool_ver4.2.1/libshm.h
uGMRT_beamutils/gptool_ver4.2.1/makefile
uGMRT_beamutils/gptool_ver4.2.1/plotgptoolsummary.py
uGMRT_beamutils/gptool_ver4.2.1/protocol.h
uGMRT_beamutils/gptool_ver4.2.1/writeCodisTotInt.c
uGMRT_beamutils/readPA/gsb_unshuf.h
uGMRT_beamutils/readPA/newcorr.h
uGMRT_beamutils/readPA/parallel_correlator.h
uGMRT_beamutils/readPA/read_PAbeam.polar.freqint.16_to_8
uGMRT_beamutils/readPA/read_PAbeam.polar.freqint.16_to_8.c
uGMRT_beamutils/readPA/read_PAbeam.polar.freqint.16_to_8.polar
uGMRT_beamutils/sigproc_install/bin/accn
uGMRT_beamutils/sigproc_install/bin/ahunt
uGMRT_beamutils/sigproc_install/bin/bandpass
uGMRT_beamutils/sigproc_install/bin/barycentre
uGMRT_beamutils/sigproc_install/bin/best
uGMRT_beamutils/sigproc_install/bin/blanker
uGMRT_beamutils/sigproc_install/bin/chaninfo
uGMRT_beamutils/sigproc_install/bin/chop_fil
uGMRT_beamutils/sigproc_install/bin/clip
uGMRT_beamutils/sigproc_install/bin/csearch
uGMRT_beamutils/sigproc_install/bin/decimate
uGMRT_beamutils/sigproc_install/bin/dedisperse
uGMRT_beamutils/sigproc_install/bin/dedisperse_all
uGMRT_beamutils/sigproc_install/bin/depolyco
uGMRT_beamutils/sigproc_install/bin/dice
uGMRT_beamutils/sigproc_install/bin/dmsampdelay
uGMRT_beamutils/sigproc_install/bin/downsample
uGMRT_beamutils/sigproc_install/bin/extract
uGMRT_beamutils/sigproc_install/bin/extragplot
uGMRT_beamutils/sigproc_install/bin/fake
uGMRT_beamds-1.1.1.dist-info/METADATA
uGMRT_beamds-1.1.1.dist-info/WHEEL
uGMRT_beamds-1.1.1.dist-info/entry_points.txt
uGMRT_beamds-1.1.1.dist-info/top_level.txt
uGMRT_beamds-1.1.1.dist-info/RECORD
