Metadata-Version: 2.1
Name: uGMRT-beamds
Version: 1.1.1
Summary: A python package to make and plot dynamic spectrum from uGMRT beamformer observations
Home-page: https://github.com/devojyoti96/uGMRT_beamds
Author: Devojyoti Kansabanik
Author-email: dkansabanik@ncra.tifr.res.in
License: UNKNOWN
Platform: UNKNOWN
Requires-Python: >=3
Requires-Dist: numpy (==1.19.0)
Requires-Dist: scipy (==1.6.2)
Requires-Dist: astropy (==4.3)
Requires-Dist: pandas
Requires-Dist: seaborn
Requires-Dist: pysigproc
